{"type":"command","pools":[{"rolls":1,"entries":[{"type":"alternatives","children":[{"type":"item","name":"cod","conditions":[{"condition":"location_check","predicate":{"block":{"state":{"facing":"east"}}}}],"functions":[{"function":"set_nbt","tag":"{Properties:{facing:east}}"}]},{"type":"item","name":"cod","conditions":[{"condition":"location_check","predicate":{"block":{"state":{"facing":"north"}}}}],"functions":[{"function":"set_nbt","tag":"{Properties:{facing:north}}"}]},{"type":"item","name":"cod","conditions":[{"condition":"location_check","predicate":{"block":{"state":{"facing":"south"}}}}],"functions":[{"function":"set_nbt","tag":"{Properties:{facing:south}}"}]},{"type":"item","name":"cod","functions":[{"function":"set_nbt","tag":"{Properties:{facing:west}}"}]}]}]}]}