{"type":"command","pools":[{"rolls":1,"entries":[{"type":"alternatives","children":[{"type":"alternatives","conditions":[{"condition":"location_check","predicate":{"block":{"state":{"layers":{"max":"4"}}}}}],"children":[{"type":"alternatives","conditions":[{"condition":"location_check","predicate":{"block":{"state":{"layers":{"max":"2"}}}}}],"children":[{"type":"item","name":"cod","conditions":[{"condition":"location_check","predicate":{"block":{"state":{"layers":"1"}}}}],"functions":[{"function":"set_nbt","tag":"{Properties:{layers:'1'}}"}]},{"type":"item","name":"cod","functions":[{"function":"set_nbt","tag":"{Properties:{layers:'2'}}"}]}]},{"type":"alternatives","children":[{"type":"item","name":"cod","conditions":[{"condition":"location_check","predicate":{"block":{"state":{"layers":"3"}}}}],"functions":[{"function":"set_nbt","tag":"{Properties:{layers:'3'}}"}]},{"type":"item","name":"cod","functions":[{"function":"set_nbt","tag":"{Properties:{layers:'4'}}"}]}]}]},{"type":"alternatives","children":[{"type":"alternatives","conditions":[{"condition":"location_check","predicate":{"block":{"state":{"layers":{"max":"6"}}}}}],"children":[{"type":"item","name":"cod","conditions":[{"condition":"location_check","predicate":{"block":{"state":{"layers":"5"}}}}],"functions":[{"function":"set_nbt","tag":"{Properties:{layers:'5'}}"}]},{"type":"item","name":"cod","functions":[{"function":"set_nbt","tag":"{Properties:{layers:'6'}}"}]}]},{"type":"alternatives","children":[{"type":"item","name":"cod","conditions":[{"condition":"location_check","predicate":{"block":{"state":{"layers":"7"}}}}],"functions":[{"function":"set_nbt","tag":"{Properties:{layers:'7'}}"}]},{"type":"item","name":"cod","functions":[{"function":"set_nbt","tag":"{Properties:{layers:'8'}}"}]}]}]}]}]}]}